md2indexhtml/__init__.py
md2indexhtml/converter.py
md2indexhtml/utils.py
md2indexhtml-0.6.0.dist-info/licenses/LICENSE
md2indexhtml-0.6.0.dist-info/METADATA
md2indexhtml-0.6.0.dist-info/WHEEL
md2indexhtml-0.6.0.dist-info/entry_points.txt
md2indexhtml-0.6.0.dist-info/top_level.txt
md2indexhtml-0.6.0.dist-info/RECORD
