Metadata-Version: 2.4
Name: md2indexhtml
Version: 0.6.0
Summary: Beautiful Markdown to HTML converter with comprehensive Odoo frontend styling
Home-page: https://github.com/fasilwdr/md2indexhtml
Author: Fasil
Author-email: Fasil <fasilwdr@hotmail.com>
License: MIT
Project-URL: Homepage, https://github.com/fasilwdr/md2indexhtml
Project-URL: Bug Reports, https://github.com/fasilwdr/md2indexhtml/issues
Project-URL: Source, https://github.com/fasilwdr/md2indexhtml
Keywords: markdown,html,odoo,documentation,frontend,styling,web,converter
Classifier: Development Status :: 4 - Beta
Classifier: Intended Audience :: Developers
Classifier: Topic :: Software Development :: Documentation
Classifier: Topic :: Text Processing :: Markup :: HTML
Classifier: Programming Language :: Python :: 3
Classifier: Programming Language :: Python :: 3.6
Classifier: Programming Language :: Python :: 3.7
Classifier: Programming Language :: Python :: 3.8
Classifier: Programming Language :: Python :: 3.9
Classifier: Programming Language :: Python :: 3.10
Classifier: Programming Language :: Python :: 3.11
Classifier: Programming Language :: Python :: 3.12
Classifier: License :: OSI Approved :: MIT License
Classifier: Operating System :: OS Independent
Requires-Python: >=3.6
License-File: LICENSE
Requires-Dist: markdown>=3.0
Dynamic: author
Dynamic: home-page
Dynamic: license-file
Dynamic: requires-python
